Workbook

Sheet Time sheet
B2: ='Control Panel'!B7 -> Abinay - BaoBunny Creatives
B5: =YEAR('Control Panel'!B12)&" "&TEXT('Control Panel'!B12,"mmm")&" Week "&'Control Panel'!B13&" Time Sheet" -> 2026 Jun Week 3 Time Sheet
B7: Timeframe: | E7: ="Week of "&TEXT('Control Panel'!B12,"m/d/yyyy")&" - "&TEXT('Control Panel'!B12+4,"m/d/yyyy") -> Week of 6/13/2026 - 6/17/2026
C10: =TEXT(C11, "DDD") -> Sat | D10: =TEXT(D11, "DDD") -> Sun | E10: =TEXT(E11, "DDD") -> Mon | F10: =TEXT(F11, "DDD") -> Tue | G10: =TEXT(G11, "DDD") -> Wed
C11: ='Control Panel'!B12 -> 46186 | D11: =C11+1 -> 46187 | E11: =D11+1 -> 46188 | F11: =E11+1 -> 46189 | G11: =F11+1 -> 46190 | H11: Totals
B12: ='Control Panel'!A22 -> Sunday Apr 19, Apr Follow-Up | C12: ='Control Panel'!B22 -> 0 | D12: ='Control Panel'!C22 -> 0 | E12: ='Control Panel'!D22 -> 0 | F12: ='Control Panel'!E22 -> 0 | G12: ='Control Panel'!F22 -> 1 | H12: =SUM(C12:G12) -> 1
B13: ='Control Panel'!A23 -> Generating HWER Complex Systems Modeling Scholar Fellowship (award) | C13: ='Control Panel'!B23 -> 0 | D13: ='Control Panel'!C23 -> 0 | E13: ='Control Panel'!D23 -> 0 | F13: ='Control Panel'!E23 -> 1 | G13: ='Control Panel'!F23 -> 0.5 | H13: =SUM(C13:G13) -> 1.5
B14: ='Control Panel'!A24 -> 0 | C14: ='Control Panel'!B24 -> 0 | D14: ='Control Panel'!C24 -> 0 | E14: ='Control Panel'!D24 -> 0 | F14: ='Control Panel'!E24 -> 0 | G14: ='Control Panel'!F24 -> 0 | H14: =SUM(C14:G14) -> 0
B15: ='Control Panel'!A25 -> 0 | C15: ='Control Panel'!B25 -> 0 | D15: ='Control Panel'!C25 -> 0 | E15: ='Control Panel'!D25 -> 0 | F15: ='Control Panel'!E25 -> 0 | G15: ='Control Panel'!F25 -> 0 | H15: =SUM(C15:G15) -> 0
B16: ='Control Panel'!A26 -> 0 | C16: ='Control Panel'!B26 -> 0 | D16: ='Control Panel'!C26 -> 0 | E16: ='Control Panel'!D26 -> 0 | F16: ='Control Panel'!E26 -> 0 | G16: ='Control Panel'!F26 -> 0 | H16: =SUM(C16:G16) -> 0
B17: Total hrs | C17: =SUM(C12:C16) -> 0 | D17: =SUM(D12:D16) -> 0 | E17: =SUM(E12:E16) -> 0 | F17: =SUM(F12:F16) -> 1 | G17: =SUM(G12:G16) -> 1.5 | H17: =SUM(H12:H16) -> 2.5
F18: Billing rate (hourly) | H18: ='Control Panel'!B14 -> 200
E19: Week Balance: | F19: =H17*H18 -> 500
E20: ="(Current Total Balance: $"&TEXT('Control Panel'!B15,"#,##0.00")&" PRIOR + $"&TEXT('Control Panel'!B17,"#,##0.00")&" NEW = $"&TEXT('Control Panel'!B18,"#,##0.00")&")" -> (Current Total Balance: $540.00 PRIOR + $500.00 NEW = $1,040.00)
B21: Output
B22: Activity | C22: Output description
B23: ='Control Panel'!A22 -> Sunday Apr 19, Apr Follow-Up | C23: ='Control Panel'!H22 -> Follow-up progress, re-definie the strategy for NIW, Future Career, Recent Priorities, and EB1A
B24: ='Control Panel'!A23 -> Generating HWER Complex Systems Modeling Scholar Fellowship (award) | C24: ='Control Panel'!H23 -> The fellowship would support Jiaman's grants efforts, train her grants writing, and network
B25: ='Control Panel'!A24 -> 0 | C25: ='Control Panel'!H24 -> 0
B26: ='Control Panel'!A25 -> 0 | C26: ='Control Panel'!H25 -> 0
B27: ='Control Panel'!A26 -> 0 | C27: ='Control Panel'!H26 -> 0
B29: Payment Record | C29: Amount | D29: Date | E29: Notes
C30: ='Control Panel'!A32 -> 500 | D30: ='Control Panel'!B32 -> Jan-26-2026 | E30: ='Control Panel'!C32 -> 0
C31: ='Control Panel'!A33 -> 600 | D31: ='Control Panel'!B33 -> Dec-10-2025 | E31: ='Control Panel'!C33 -> 0
C32: ='Control Panel'!A34 -> 200 | D32: ='Control Panel'!B34 -> Mar-03-2026 | E32: ='Control Panel'!C34 -> 0
C33: ='Control Panel'!A35 -> 200 | D33: ='Control Panel'!B35 -> Apr-01-2026 | E33: ='Control Panel'!C35 -> 0
C34: ='Control Panel'!A36 -> 0 | D34: ='Control Panel'!B36 -> 0 | E34: ='Control Panel'!C36 -> 0
B36: ="$"&TEXT('Control Panel'!B19,"#,##0.00")&"/$"&TEXT('Control Panel'!B16,"#,##0.00")&" max" -> $1,500.00/$100,000.00 max | C36: ='Control Panel'!B8 -> will apply for NIW when estimated successful rate over 80%
B37: ='Control Panel'!B9 -> Date for Payment (every month 1st, $200 per mon, until balance is fully paid)

Sheet Stats
B3: Utilization | D3: See breakdowns of your week by project or day. Everything in this tab updates from the Time sheet tab and Control Panel.
B5: By Project
F8: {='Time sheet'!B12:B16} -> Sunday Apr 19, Apr Follow-Up | G8: {='Time sheet'!H12:H16} -> 1
F9: Generating HWER Complex Systems Modeling Scholar Fellowship (award) | G9: 1.5
F10: 0 | G10: 0
F11: 0 | G11: 0
F12: 0 | G12: 0
B25: Per Day
F28: {=TRANSPOSE('Time sheet'!$C$10:$G$10)} -> Sat | G28: {=TRANSPOSE('Time sheet'!$C$17:$G$17)} -> 0
F29: Sun | G29: 0
F30: Mon | G30: 0
F31: Tue | G31: 1
F32: Wed | G32: 1.5

Sheet Control Panel
A1: Timesheet Control Panel
A3: 1) Customer + Contract | F3: Live Preview
A4: Select existing customer | B4: Abinay | D4: Select an existing customer from the Customers sheet. | F4: Customer | G4: =B7 -> Abinay - BaoBunny Creatives
A5: New customer name (optional) | D5: Or type a brand-new customer name here. | F5: Title | G5: =YEAR(B12)&" "&TEXT(B12,"mmm")&" Week "&B13&" Time Sheet" -> 2026 Jun Week 3 Time Sheet
A6: Company / project override | B6: BaoBunny Creatives | D6: Optional company / project text that appears after the customer name. | F6: Timeframe | G6: ="Week of "&TEXT(B12,"m/d/yyyy")&" - "&TEXT(B12+4,"m/d/yyyy") -> Week of 6/13/2026 - 6/17/2026
A7: Active customer display | B7: =IF(B5<>"",B5,B4)&IF(B6<>""," - "&B6,IFERROR(" - "&VLOOKUP(B4,Customers!$A$2:$B$100,2,FALSE),"")) -> Abinay - BaoBunny Creatives
A8: Contract / spending note | B8: will apply for NIW when estimated successful rate over 80% | F8: Hours | G8: =SUM(G22:G26) -> 2.5
A9: Footnote | B9: Date for Payment (every month 1st, $200 per mon, until balance is fully paid) | F9: New balance | G9: =B17 -> 500
F10: Current balance | G10: =B18 -> 1040
A11: 2) Week Setup
A12: Week start date (Mon) | B12: 46186
A13: Week number | B13: 3
A14: Hourly rate | B14: 200 | D14: You can overwrite the default rate if needed.
A15: Prior balance | B15: 540
A16: Max contract spend | B16: 100000 | D16: You can overwrite the default contract max if needed.
A17: New balance (this week) | B17: =SUM(G22:G26)*B14 -> 500
A18: Current total balance | B18: =B15+B17 -> 1040
A19: Total expenses / payments | B19: =SUM(A32:A36) -> 1500
A21: 3) Activities | B21: Mon | C21: Tue | D21: Wed | E21: Thu | F21: Fri | G21: Total | H21: Output description
A22: Sunday Apr 19, Apr Follow-Up | B22: 0 | C22: 0 | D22: 0 | E22: 0 | F22: 1 | G22: =SUM(B22:F22) -> 1 | H22: Follow-up progress, re-definie the strategy for NIW, Future Career, Recent Priorities, and EB1A
A23: Generating HWER Complex Systems Modeling Scholar Fellowship (award) | B23: 0 | C23: 0 | D23: 0 | E23: 1 | F23: 0.5 | G23: =SUM(B23:F23) -> 1.5 | H23: The fellowship would support Jiaman's grants efforts, train her grants writing, and network
B24: 0 | C24: 0 | D24: 0 | E24: 0 | F24: 0 | G24: =SUM(B24:F24) -> 0
B25: 0 | C25: 0 | D25: 0 | E25: 0 | F25: 0 | G25: =SUM(B25:F25) -> 0
B26: 0 | C26: 0 | D26: 0 | E26: 0 | F26: 0 | G26: =SUM(B26:F26) -> 0
A30: 4) Payment Records
A31: Amount | B31: Payment date | C31: Notes
A32: 500 | B32: Jan-26-2026 | D32: Add up to 5 payment records here.
A33: 600 | B33: Dec-10-2025
A34: 200 | B34: Mar-03-2026
A35: 200 | B35: Apr-01-2026

Sheet Customers
A1: Customer Name | B1: Company / Project | C1: Default Hourly Rate | D1: Max Contract Spend | E1: Notes
A2: Jiaman | B2: BaoBunny Creatives | C2: 200 | D2: 10000 | E2: will apply for NIW when estimated successful rate over 80%
A4: How to use | B4: Add one customer per row below the example. Then select the customer on the Control Panel sheet.
A21: Abinay | B21: BaoBunny Creatives | C21: 200 | D21: 10000 | E21: will apply for NIW when estimated successful rate over 80%

Sheet Client Timesheet
B2: ='Control Panel'!B7 -> Abinay - BaoBunny Creatives
B5: =YEAR('Control Panel'!B12)&" "&TEXT('Control Panel'!B12,"mmm")&" Week "&'Control Panel'!B13&" Time Sheet" -> 2026 Jun Week 3 Time Sheet
B7: Timeframe: | E7: ="Week of "&TEXT('Control Panel'!B12,"m/d/yyyy")&" - "&TEXT('Control Panel'!B12+4,"m/d/yyyy") -> Week of 6/13/2026 - 6/17/2026
C10: Mon | D10: Tue | E10: Wed | F10: Thu | G10: Fri | H10: Totals
C11: ='Control Panel'!B12 -> 46186 | D11: ='Control Panel'!B12+1 -> 46187 | E11: ='Control Panel'!B12+2 -> 46188 | F11: ='Control Panel'!B12+3 -> 46189 | G11: ='Control Panel'!B12+4 -> 46190
B12: =IF('Control Panel'!A22="","",'Control Panel'!A22) -> Sunday Apr 19, Apr Follow-Up | C12: =IF($B12="","",'Control Panel'!B22) -> 0 | D12: =IF($B12="","",'Control Panel'!C22) -> 0 | E12: =IF($B12="","",'Control Panel'!D22) -> 0 | F12: =IF($B12="","",'Control Panel'!E22) -> 0 | G12: =IF($B12="","",'Control Panel'!F22) -> 1 | H12: =IF($B12="","",SUM(C12:G12)) -> 1
B13: =IF('Control Panel'!A23="","",'Control Panel'!A23) -> Generating HWER Complex Systems Modeling Scholar Fellowship (award) | C13: =IF($B13="","",'Control Panel'!B23) -> 0 | D13: =IF($B13="","",'Control Panel'!C23) -> 0 | E13: =IF($B13="","",'Control Panel'!D23) -> 0 | F13: =IF($B13="","",'Control Panel'!E23) -> 1 | G13: =IF($B13="","",'Control Panel'!F23) -> 0.5 | H13: =IF($B13="","",SUM(C13:G13)) -> 1.5
B14: =IF('Control Panel'!A24="","",'Control Panel'!A24) | C14: =IF($B14="","",'Control Panel'!B24) | D14: =IF($B14="","",'Control Panel'!C24) | E14: =IF($B14="","",'Control Panel'!D24) | F14: =IF($B14="","",'Control Panel'!E24) | G14: =IF($B14="","",'Control Panel'!F24) | H14: =IF($B14="","",SUM(C14:G14))
B15: =IF('Control Panel'!A25="","",'Control Panel'!A25) | C15: =IF($B15="","",'Control Panel'!B25) | D15: =IF($B15="","",'Control Panel'!C25) | E15: =IF($B15="","",'Control Panel'!D25) | F15: =IF($B15="","",'Control Panel'!E25) | G15: =IF($B15="","",'Control Panel'!F25) | H15: =IF($B15="","",SUM(C15:G15))
B16: =IF('Control Panel'!A26="","",'Control Panel'!A26) | C16: =IF($B16="","",'Control Panel'!B26) | D16: =IF($B16="","",'Control Panel'!C26) | E16: =IF($B16="","",'Control Panel'!D26) | F16: =IF($B16="","",'Control Panel'!E26) | G16: =IF($B16="","",'Control Panel'!F26) | H16: =IF($B16="","",SUM(C16:G16))
B17: Total hrs | C17: =SUM(C12:C16) -> 0 | D17: =SUM(D12:D16) -> 0 | E17: =SUM(E12:E16) -> 0 | F17: =SUM(F12:F16) -> 1 | G17: =SUM(G12:G16) -> 1.5 | H17: =SUM(C17:G17) -> 2.5
F18: Billing rate (hourly) | H18: ='Control Panel'!B14 -> 200
E19: Week Balance: | H19: ='Control Panel'!B17 -> 500
E20: ="(Current Total Balance: $"&TEXT('Control Panel'!B15,"#,##0.00")&" PRIOR + $"&TEXT('Control Panel'!B17,"#,##0.00")&" NEW = $"&TEXT('Control Panel'!B18,"#,##0.00")&")" -> (Current Total Balance: $540.00 PRIOR + $500.00 NEW = $1,040.00)
B22: Output
B23: Activity | C23: Output description
B24: =IF('Control Panel'!A22="","",'Control Panel'!A22) -> Sunday Apr 19, Apr Follow-Up | C24: =IF('Control Panel'!A22="","",'Control Panel'!H22) -> Follow-up progress, re-definie the strategy for NIW, Future Career, Recent Priorities, and EB1A
B25: =IF('Control Panel'!A23="","",'Control Panel'!A23) -> Generating HWER Complex Systems Modeling Scholar Fellowship (award) | C25: =IF('Control Panel'!A23="","",'Control Panel'!H23) -> The fellowship would support Jiaman's grants efforts, train her grants writing, and network
B26: =IF('Control Panel'!A24="","",'Control Panel'!A24) | C26: =IF('Control Panel'!A24="","",'Control Panel'!H24)
B27: =IF('Control Panel'!A25="","",'Control Panel'!A25) | C27: =IF('Control Panel'!A25="","",'Control Panel'!H25)
B28: =IF('Control Panel'!A26="","",'Control Panel'!A26) | C28: =IF('Control Panel'!A26="","",'Control Panel'!H26)
B30: Payment Record | C30: Amount | D30: Date | E30: Notes
C31: =IF('Control Panel'!A32="","",'Control Panel'!A32) -> 500 | D31: =IF('Control Panel'!A32="","",'Control Panel'!B32) -> Jan-26-2026 | E31: =IF('Control Panel'!A32="","",'Control Panel'!C32) -> 0
C32: =IF('Control Panel'!A33="","",'Control Panel'!A33) -> 600 | D32: =IF('Control Panel'!A33="","",'Control Panel'!B33) -> Dec-10-2025 | E32: =IF('Control Panel'!A33="","",'Control Panel'!C33) -> 0
C33: =IF('Control Panel'!A34="","",'Control Panel'!A34) -> 200 | D33: =IF('Control Panel'!A34="","",'Control Panel'!B34) -> Mar-03-2026 | E33: =IF('Control Panel'!A34="","",'Control Panel'!C34) -> 0
C34: =IF('Control Panel'!A35="","",'Control Panel'!A35) -> 200 | D34: =IF('Control Panel'!A35="","",'Control Panel'!B35) -> Apr-01-2026 | E34: =IF('Control Panel'!A35="","",'Control Panel'!C35) -> 0
C35: =IF('Control Panel'!A36="","",'Control Panel'!A36) | D35: =IF('Control Panel'!A36="","",'Control Panel'!B36) | E35: =IF('Control Panel'!A36="","",'Control Panel'!C36)
B37: Total expenses | C37: ='Control Panel'!B19 -> 1500 | E37: Max contract spend | F37: ='Control Panel'!B16 -> 100000
B38: Contract note | C38: ='Control Panel'!B8 -> will apply for NIW when estimated successful rate over 80%
B39: Footnote | C39: ='Control Panel'!B9 -> Date for Payment (every month 1st, $200 per mon, until balance is fully paid)
